igwn_auth_utils/__init__.py
igwn_auth_utils/_version.py
igwn_auth_utils/error.py
igwn_auth_utils/kerberos.py
igwn_auth_utils/requests.py
igwn_auth_utils/scitokens.py
igwn_auth_utils/x509.py
igwn_auth_utils/tests/__init__.py
igwn_auth_utils/tests/conftest.py
igwn_auth_utils/tests/test_kerberos.py
igwn_auth_utils/tests/test_requests.py
igwn_auth_utils/tests/test_scitokens.py
igwn_auth_utils/tests/test_x509.py
igwn_auth_utils-1.3.1.dist-info/licenses/LICENSE
igwn_auth_utils-1.3.1.dist-info/METADATA
igwn_auth_utils-1.3.1.dist-info/WHEEL
igwn_auth_utils-1.3.1.dist-info/top_level.txt
igwn_auth_utils-1.3.1.dist-info/RECORD
