Metadata-Version: 2.4
Name: igwn-auth-utils
Version: 1.3.1
Summary: Authorisation utilities for IGWN
Author-email: Duncan Macleod <duncan.macleod@ligo.org>
License: BSD-3-Clause
Project-URL: Homepage, https://git.ligo.org/computing/igwn-auth-utils/
Project-URL: Bug Tracker, https://git.ligo.org/computing/igwn-auth-utils/-/issues/
Project-URL: Documentation, https://igwn-auth-utils.readthedocs.io
Project-URL: Source Code, https://git.ligo.org/computing/igwn-auth-utils.git
Classifier: Development Status :: 5 - Production/Stable
Classifier: Intended Audience :: Developers
Classifier: Intended Audience :: End Users/Desktop
Classifier: Intended Audience :: Science/Research
Classifier: License :: OSI Approved :: BSD License
Classifier: Natural Language :: English
Classifier: Operating System :: OS Independent
Classifier: Programming Language :: Python
Classifier: Programming Language :: Python :: 3
Classifier: Programming Language :: Python :: 3.6
Classifier: Programming Language :: Python :: 3.7
Classifier: Programming Language :: Python :: 3.8
Classifier: Programming Language :: Python :: 3.9
Classifier: Programming Language :: Python :: 3.10
Classifier: Programming Language :: Python :: 3.11
Classifier: Programming Language :: Python :: 3.12
Classifier: Programming Language :: Python :: 3.13
Classifier: Topic :: Scientific/Engineering
Classifier: Topic :: Scientific/Engineering :: Astronomy
Classifier: Topic :: Scientific/Engineering :: Physics
Requires-Python: >=3.9
License-File: LICENSE
Requires-Dist: cryptography>=44.0.1
Requires-Dist: requests>=2.32.0
Requires-Dist: safe-netrc>=1.0
Requires-Dist: scitokens>=1.8
Provides-Extra: gettoken
Requires-Dist: htgettoken>=2.1; extra == "gettoken"
Provides-Extra: kerberos
Requires-Dist: gssapi>=1.9.0; extra == "kerberos"
Provides-Extra: docs
Requires-Dist: furo; extra == "docs"
Requires-Dist: Sphinx>=4.0.0; extra == "docs"
Requires-Dist: sphinx-automodapi; extra == "docs"
Requires-Dist: sphinx-copybutton; extra == "docs"
Requires-Dist: sphinx-github-style; extra == "docs"
Provides-Extra: test
Requires-Dist: pytest>=3.9.1; extra == "test"
Requires-Dist: pytest-cov; extra == "test"
Requires-Dist: requests-mock; extra == "test"
Dynamic: license-file
